xmscore/__init__.py
xmscore/_xmscore.cp36-win_amd64.pyd
xmscore/misc/__init__.py
xmscore/misc/observer.py
xmscore-3.0.2.dist-info/METADATA
xmscore-3.0.2.dist-info/WHEEL
xmscore-3.0.2.dist-info/top_level.txt
xmscore-3.0.2.dist-info/RECORD
